koolnova_api/__init__.py
koolnova_api/client.py
koolnova_api/const.py
koolnova_api/exceptions.py
koolnova_api/session.py
koolnova_api-1.1.5.dist-info/LICENSE
koolnova_api-1.1.5.dist-info/METADATA
koolnova_api-1.1.5.dist-info/WHEEL
koolnova_api-1.1.5.dist-info/RECORD
