Metadata-Version: 2.3
Name: koolnova-api
Version: 1.1.5
Summary: Python client for Koolnova API.
License: GPL-3.0-or-later
Keywords: koolnova,koolnova-api,clim
Author: bedav31
Requires-Python: >=3.10.0,<4.0.0
Classifier: Development Status :: 5 - Production/Stable
Classifier: License :: OSI Approved :: GNU General Public License v3 or later (GPLv3+)
Classifier: Operating System :: OS Independent
Classifier: Programming Language :: Python :: 3
Classifier: Programming Language :: Python :: 3.10
Classifier: Programming Language :: Python :: 3.11
Classifier: Programming Language :: Python :: 3.12
Classifier: Programming Language :: Python :: 3.13
Requires-Dist: python-dateutil (>=2.7.0,<3.0.0)
Requires-Dist: requests (>=2.25.0,<3.0.0)
